texas_hold_em_utils/__init__.py
texas_hold_em_utils/card.py
texas_hold_em_utils/deck.py
texas_hold_em_utils/game.py
texas_hold_em_utils/game_utils.py
texas_hold_em_utils/hands.py
texas_hold_em_utils/outs_counter.py
texas_hold_em_utils/player.py
texas_hold_em_utils/post_flop_stats_repository.py
texas_hold_em_utils/preflop_stats_repository.py
texas_hold_em_utils/relative_ranking.py
texas_hold_em_utils/sklansky.py
texas_hold_em_utils/texas_hold_em_utils.md
texas_hold_em_utils/data/post_flop_win_rate_distribution.csv
texas_hold_em_utils/data/preflop_win_rates.csv
texas_hold_em_utils-0.1.17.dist-info/METADATA
texas_hold_em_utils-0.1.17.dist-info/WHEEL
texas_hold_em_utils-0.1.17.dist-info/licenses/LICENSE
texas_hold_em_utils-0.1.17.dist-info/RECORD
