Metadata-Version: 2.4
Name: texas_hold_em_utils
Version: 0.1.17
Summary: A package containing the logic for a Texas Hold 'Em game, along with some related utilities.
Project-URL: Homepage, https://github.com/amarkules1/texas-hold-em
Project-URL: Issues, https://github.com/amarkules1/texas-hold-em/issues
Author-email: Alex Markules <amarlar2354@gmail.com>
License-Expression: MIT
License-File: LICENSE
Classifier: Operating System :: OS Independent
Classifier: Programming Language :: Python :: 3
Requires-Python: >=3.8
